setup.cfg
setup.py
Eggcelerator.egg-info/PKG-INFO
Eggcelerator.egg-info/SOURCES.txt
Eggcelerator.egg-info/dependency_links.txt
Eggcelerator.egg-info/entry_points.txt
Eggcelerator.egg-info/not-zip-safe
Eggcelerator.egg-info/requires.txt
Eggcelerator.egg-info/top_level.txt
eggcelerator/__init__.py
eggcelerator/main.py
scripts/eggcelerator