Metadata-Version: 1.0
Name: Eggcelerator
Version: 0.1dev-20120905
Summary: Compiles your packages into binary eggs and caches them
Home-page: UNKNOWN
Author: UNKNOWN
Author-email: UNKNOWN
License: UNKNOWN
Platform: UNKNOWN
